sysmp/__init__.py
sysmp-0.1.0.dist-info/METADATA
sysmp-0.1.0.dist-info/WHEEL
sysmp-0.1.0.dist-info/RECORD
