Metadata-Version: 2.1
Name: sysmp
Version: 0.1.0
Summary: The simple py api
Author: Andrew Coder
Requires-Python: >=3.11,<4.0
Classifier: Programming Language :: Python :: 3
Classifier: Programming Language :: Python :: 3.11
